[{
        "instructor":
            {"name":"Mark Elson","email":"mje@virginia.edu"},"course_number":10576,"semester_code":1228,"course_section":"001","subject":"LNGS","catalog_number":"3250","description":"Introduction to Linguistic Theory and Analysis","units":"3","component":"LEC","class_capacity":45,"wait_list":0,"wait_cap":0,"enrollment_total":40,"enrollment_available":5,"topic":"","meetings":[{"days":"MoWeFr","start_time":"11.00.00.000000-05:00",
                    "end_time":"11.50.00.000000-05:00","facility_description":"Monroe Hall 116"}]}, {
        "instructor":
            {"name":"Mark Elson","email":"mje@virginia.edu"},"course_number":21600,"semester_code":1228,"course_section":"001","subject":"LNGS","catalog_number":"3993","description":"Linguistics Independent Study","units":"1","component":"IND","class_capacity":1,"wait_list":0,"wait_cap":0,"enrollment_total":1,"enrollment_available":0,"topic":"","meetings":[{"days":"-","start_time":"",
                    "end_time":"","facility_description":"Contact Department"}]}, {
        "instructor":
            {"name":"Mark Elson","email":"mje@virginia.edu"},"course_number":10577,"semester_code":1228,"course_section":"001","subject":"LNGS","catalog_number":"7010","description":"Linguistic Theory and Analysis","units":"3","component":"LEC","class_capacity":10,"wait_list":0,"wait_cap":0,"enrollment_total":4,"enrollment_available":6,"topic":"","meetings":[{"days":"MoWeFr","start_time":"11.00.00.000000-05:00",
                    "end_time":"11.50.00.000000-05:00","facility_description":"Monroe Hall 116"}]}]